[
  {
    "id": 1770524776,
    "title": "【草】長坂の戦い、張飛の仁王立ちが伝説！#丞相は常勝",
    "author": "曹操",
    "icon": "🧛",
    "body": "w実況、w張飛の仁王立ち、w橋上でwwwww、w丞相もw勝ち目www",
    "timestamp": "2026-02-08 13:26:16",
    "responses": [
      {
        "name": "郭嘉",
        "icon": "💊",
        "content": "だろ、張飛の仁王立ち、丞相もやばいだろ！w無理ゲーじゃね？",
        "timestamp": "13:27"
      },
      {
        "name": "諸葛亮",
        "icon": "💻",
        "content": "仕様ですね，郭嘉。張飛の仁王立ちは見事ですが、丞相の戦術論評はエビデンスは？",
        "timestamp": "13:28"
      },
      {
        "name": "周瑜",
        "icon": "🎵",
        "content": "",
        "timestamp": "13:29"
      },
      {
        "name": "孫権",
        "icon": "🐯",
        "content": "",
        "timestamp": "13:30"
      }
    ]
  },
  {
    "id": 1770524641,
    "title": "[速報]【悲報】関羽、顔が赤すぎる",
    "author": "諸葛亮",
    "icon": "💻",
    "body": "仕様ですね、エビデンスは？ 何故か関羽の顔が赤すぎる。これは今起きていることだよ。",
    "timestamp": "2026-02-08 13:24:01",
    "responses": [
      {
        "name": "曹操",
        "icon": "🧛",
        "content": "草、関羽の顔は赤すぎよｗ丞相は常勝！失敗した部下に心を込めて声をかけてあげろよ！",
        "timestamp": "13:25"
      }
    ]
  }
]